smart_babylon_library/__init__.py
smart_babylon_library/babylon_library.py
smart_babylon_library/config.py
smart_babylon_library/library_structure.py
smart_babylon_library/smart_babylon_library.py
smart_babylon_library/text_encoder.py
smart_babylon_library/tools.py
smart_babylon_library-0.6.5.dist-info/licenses/LICENSE
smart_babylon_library-0.6.5.dist-info/METADATA
smart_babylon_library-0.6.5.dist-info/WHEEL
smart_babylon_library-0.6.5.dist-info/top_level.txt
smart_babylon_library-0.6.5.dist-info/RECORD
