Metadata-Version: 2.4
Name: smart-babylon-library
Version: 0.6.5
Summary: A Python library for creating and manipulating text libraries, inspired by the Library of Babel concept and my own concept of Smart Passwords.
Author-email: "A.A. Suvorov" <smartlegiondev@gmail.com>
License-Expression: BSD-3-Clause
Project-URL: Homepage, https://github.com/smartlegionlab/smart-babylon-library
Classifier: Programming Language :: Python :: 3
Classifier: Operating System :: OS Independent
Requires-Python: >=3.6
License-File: LICENSE
Dynamic: license-file
